{"chunk_definitions":[{"chunk_id":"cc66oj26d7i4j","chunk_label":"unnamed-chunk-1","document_id":"B4B7B69B","expansion_state":0,"options":{"engine":"r","label":"unnamed-chunk-1"},"row":17,"row_count":1,"visible":true},{"chunk_id":"cgfw5jcvrho9k","chunk_label":"unnamed-chunk-2","document_id":"B4B7B69B","expansion_state":0,"options":{"engine":"r","label":"unnamed-chunk-3"},"row":61,"row_count":1,"visible":true},{"chunk_id":"c9jwcju4zj84y","chunk_label":"unnamed-chunk-3","document_id":"B4B7B69B","expansion_state":0,"options":{"engine":"r","label":"unnamed-chunk-3"},"row":72,"row_count":1,"visible":true},{"chunk_id":"chha4kkry121u","chunk_label":"unnamed-chunk-4","document_id":"7613AA02","expansion_state":0,"options":{"engine":"r","label":"unnamed-chunk-4"},"row":122,"row_count":1,"visible":true}],"doc_write_time":1649799116}